<annotation>
    <folder>VOC2007</folder>
    <filename>003430.jpg</filename>
    <source>
        <database>The CCF2017 Database</database>
        <annotation>PASCAL CCF2017</annotation>
        <image>flickr</image>
        <flickrid>000000000</flickrid>
    </source>
    <owner>
        <flickrid>?</flickrid>
        <name>?</name>
    </owner>
    <size>
        <width>0</width>
        <height>0</height>
        <depth>3</depth>
    </size>
    <segmented>0</segmented>
    <object>
        <name>0007</name>
        <pose>Unspecified</pose>
        <truncated>0</truncated>
        <difficult>0</difficult>
        <bndbox>
            <xmin>157</xmin>
            <ymin>623</ymin>
            <xmax>176</xmax>
            <ymax>669</ymax>
        </bndbox>
    </object>
    <object>
        <name>0011</name>
        <pose>Unspecified</pose>
        <truncated>0</truncated>
        <difficult>0</difficult>
        <bndbox>
            <xmin>169</xmin>
            <ymin>307</ymin>
            <xmax>197</xmax>
            <ymax>373</ymax>
        </bndbox>
    </object>
    <object>
        <name>0014</name>
        <pose>Unspecified</pose>
        <truncated>0</truncated>
        <difficult>0</difficult>
        <bndbox>
            <xmin>327</xmin>
            <ymin>333</ymin>
            <xmax>338</xmax>
            <ymax>339</ymax>
        </bndbox>
    </object>
    <object>
        <name>0017</name>
        <pose>Unspecified</pose>
        <truncated>0</truncated>
        <difficult>0</difficult>
        <bndbox>
            <xmin>66</xmin>
            <ymin>78</ymin>
            <xmax>72</xmax>
            <ymax>95</ymax>
        </bndbox>
    </object>
    <object>
        <name>0018</name>
        <pose>Unspecified</pose>
        <truncated>0</truncated>
        <difficult>0</difficult>
        <bndbox>
            <xmin>69</xmin>
            <ymin>666</ymin>
            <xmax>75</xmax>
            <ymax>676</ymax>
        </bndbox>
    </object>
</annotation>
