<annotation>
    <folder>VOC2007</folder>
    <filename>003660.jpg</filename>
    <source>
        <database>The CCF2017 Database</database>
        <annotation>PASCAL CCF2017</annotation>
        <image>flickr</image>
        <flickrid>000000000</flickrid>
    </source>
    <owner>
        <flickrid>?</flickrid>
        <name>?</name>
    </owner>
    <size>
        <width>0</width>
        <height>0</height>
        <depth>3</depth>
    </size>
    <segmented>0</segmented>
    <object>
        <name>0008</name>
        <pose>Unspecified</pose>
        <truncated>0</truncated>
        <difficult>0</difficult>
        <bndbox>
            <xmin>697</xmin>
            <ymin>171</ymin>
            <xmax>720</xmax>
            <ymax>193</ymax>
        </bndbox>
    </object>
    <object>
        <name>0009</name>
        <pose>Unspecified</pose>
        <truncated>0</truncated>
        <difficult>0</difficult>
        <bndbox>
            <xmin>708</xmin>
            <ymin>356</ymin>
            <xmax>797</xmax>
            <ymax>447</ymax>
        </bndbox>
    </object>
    <object>
        <name>0024</name>
        <pose>Unspecified</pose>
        <truncated>0</truncated>
        <difficult>0</difficult>
        <bndbox>
            <xmin>328</xmin>
            <ymin>374</ymin>
            <xmax>339</xmax>
            <ymax>386</ymax>
        </bndbox>
    </object>
</annotation>
